logwatch_analyzer-0.1.10.2.dist-info/licenses/LICENSE
logwatch_cli/__init__.py
logwatch_cli/config.yaml
logwatch_cli/main.py
logwatch_analyzer-0.1.10.2.dist-info/METADATA
logwatch_analyzer-0.1.10.2.dist-info/WHEEL
logwatch_analyzer-0.1.10.2.dist-info/entry_points.txt
logwatch_analyzer-0.1.10.2.dist-info/top_level.txt
logwatch_analyzer-0.1.10.2.dist-info/RECORD
