Metadata-Version: 2.4
Name: logwatch-analyzer
Version: 0.1.10.2
Summary: A CLI tool to analyze journalctl logs with specific parsers and LLM integration.
Author-email: Your Name <your@email.com>
License: MIT License
Project-URL: Homepage, https://github.com/your-username/logwatch
Project-URL: Bug Tracker, https://github.com/your-username/logwatch/issues
Classifier: Programming Language :: Python :: 3
Classifier: License :: OSI Approved :: MIT License
Classifier: Operating System :: OS Independent
Classifier: Environment :: Console
Classifier: Topic :: System :: Logging
Requires-Python: >=3.8
License-File: LICENSE
Requires-Dist: PyYAML
Requires-Dist: requests
Requires-Dist: rich
Dynamic: license-file
